nanomanifold/__init__.py
nanomanifold/common.py
nanomanifold/SE3/__init__.py
nanomanifold/SE3/canonicalize.py
nanomanifold/SE3/exp.py
nanomanifold/SE3/inverse.py
nanomanifold/SE3/log.py
nanomanifold/SE3/multiply.py
nanomanifold/SE3/transform_points.py
nanomanifold/SE3/conversions/__init__.py
nanomanifold/SE3/conversions/matrix.py
nanomanifold/SE3/conversions/rt.py
nanomanifold/SO3/__init__.py
nanomanifold/SO3/canonicalize.py
nanomanifold/SO3/distance.py
nanomanifold/SO3/exp.py
nanomanifold/SO3/hat.py
nanomanifold/SO3/inverse.py
nanomanifold/SO3/log.py
nanomanifold/SO3/multiply.py
nanomanifold/SO3/rotate_points.py
nanomanifold/SO3/slerp.py
nanomanifold/SO3/vee.py
nanomanifold/SO3/weighted_mean.py
nanomanifold/SO3/conversions/__init__.py
nanomanifold/SO3/conversions/axis_angle.py
nanomanifold/SO3/conversions/euler.py
nanomanifold/SO3/conversions/matrix.py
nanomanifold-0.1.2.dist-info/METADATA
nanomanifold-0.1.2.dist-info/WHEEL
nanomanifold-0.1.2.dist-info/licenses/LICENSE
nanomanifold-0.1.2.dist-info/RECORD
