Metadata-Version: 2.4
Name: nanomanifold
Version: 0.1.2
Summary: SO3/SE3 operations on any backend
Author-email: Andrea Boscolo Camiletto <abcamiletto@gmail.com>
License-File: LICENSE
Requires-Python: >=3.10
Requires-Dist: array-api-compat>=1.12.0
Requires-Dist: jaxtyping>=0.3.2
Requires-Dist: numpy>=2.2.0
